examon_python_one_liners_repo/__init__.py
examon_python_one_liners_repo/questions.py
examon_python_one_liners_repo-0.0.1.dist-info/METADATA
examon_python_one_liners_repo-0.0.1.dist-info/WHEEL
examon_python_one_liners_repo-0.0.1.dist-info/RECORD
