Metadata-Version: 2.1
Name: examon-python-one-liners-repo
Version: 0.0.1
Summary: 
Author: Jarrod Folino
Author-email: jdfolino@icloud.com
Requires-Python: >3.9,<3.12
Classifier: Programming Language :: Python :: 3
Classifier: Programming Language :: Python :: 3.10
Classifier: Programming Language :: Python :: 3.11
Requires-Dist: examon-core (==1.2.3)
